mcp_serializer/__init__.py
mcp_serializer/contexts.py
mcp_serializer/errors.py
mcp_serializer/features/base/__init__.py
mcp_serializer/features/base/assembler.py
mcp_serializer/features/base/container.py
mcp_serializer/features/base/contents.py
mcp_serializer/features/base/definitions.py
mcp_serializer/features/base/pagination.py
mcp_serializer/features/base/parsers.py
mcp_serializer/features/base/schema.py
mcp_serializer/features/prompt/__init__.py
mcp_serializer/features/prompt/assembler.py
mcp_serializer/features/prompt/container.py
mcp_serializer/features/prompt/result.py
mcp_serializer/features/prompt/schema.py
mcp_serializer/features/resource/__init__.py
mcp_serializer/features/resource/assembler.py
mcp_serializer/features/resource/container.py
mcp_serializer/features/resource/result.py
mcp_serializer/features/resource/schema.py
mcp_serializer/features/tool/__init__.py
mcp_serializer/features/tool/assembler.py
mcp_serializer/features/tool/container.py
mcp_serializer/features/tool/result.py
mcp_serializer/features/tool/schema.py
mcp_serializer/initializer.py
mcp_serializer/logging.py
mcp_serializer/managers.py
mcp_serializer/registry.py
mcp_serializer/results.py
mcp_serializer/schema.py
mcp_serializer/serializers.py
mcp_serializer-1.2.2.dist-info/METADATA
mcp_serializer-1.2.2.dist-info/WHEEL
mcp_serializer-1.2.2.dist-info/licenses/LICENSE
mcp_serializer-1.2.2.dist-info/RECORD
