Metadata-Version: 2.4
Name: mcp-serializer
Version: 1.2.2
Summary: Register MCP features and serialize JSON-RPC requests into response data
License: MIT
License-File: LICENSE
Author: Amir Ebrahim md.amire02@gmail.com
Requires-Python: >=3.9
Classifier: License :: OSI Approved :: MIT License
Classifier: Programming Language :: Python :: 3
Classifier: Programming Language :: Python :: 3.9
Classifier: Programming Language :: Python :: 3.10
Classifier: Programming Language :: Python :: 3.11
Classifier: Programming Language :: Python :: 3.12
Classifier: Programming Language :: Python :: 3.13
Classifier: Programming Language :: Python :: 3.14
Requires-Dist: pydantic (>=2.11.10,<3.0.0)
Project-URL: Changelog, https://github.com/mdamire/mcp-serializer/blob/master/CHANGELOG.md
Project-URL: Homepage, https://github.com/mdamire/mcp-serializer
Project-URL: Repository, https://github.com/mdamire/mcp-serializer
